scrywarden/__init__.py
scrywarden/cli.py
scrywarden/database.py
scrywarden/entry.py
scrywarden/exceptions.py
scrywarden/missing.py
scrywarden/module.py
scrywarden/timing.py
scrywarden/typing.py
scrywarden/config/__init__.py
scrywarden/config/base.py
scrywarden/config/exceptions.py
scrywarden/config/logging.py
scrywarden/config/parsers.py
scrywarden/config/settings.py
scrywarden/curator/__init__.py
scrywarden/curator/base.py
scrywarden/curator/entry.py
scrywarden/investigator/__init__.py
scrywarden/investigator/base.py
scrywarden/investigator/entry.py
scrywarden/pipline/__init__.py
scrywarden/pipline/base.py
scrywarden/pipline/entry.py
scrywarden/profile/__init__.py
scrywarden/profile/analyzers.py
scrywarden/profile/base.py
scrywarden/profile/collectors.py
scrywarden/profile/config.py
scrywarden/profile/example.py
scrywarden/profile/fields.py
scrywarden/profile/reporters.py
scrywarden/shipper/__init__.py
scrywarden/shipper/base.py
scrywarden/shipper/config.py
scrywarden/shipper/csv.py
scrywarden/shipper/logger.py
scrywarden/transport/__init__.py
scrywarden/transport/base.py
scrywarden/transport/config.py
scrywarden/transport/csv.py
scrywarden/transport/entry.py
scrywarden/transport/heartbeat.py
scrywarden/transport/message.py
scrywarden-0.1.1.dist-info/LICENSE
scrywarden-0.1.1.dist-info/METADATA
scrywarden-0.1.1.dist-info/WHEEL
scrywarden-0.1.1.dist-info/entry_points.txt
scrywarden-0.1.1.dist-info/top_level.txt
scrywarden-0.1.1.dist-info/RECORD
