Metadata-Version: 2.1
Name: scrywarden
Version: 0.1.1
Summary: Detect anomalies in datasets using behavioral modeling
Home-page: https://github.com/chasebrewsky/scrywarden
Author: Chase Brewer
Author-email: chasebrewsky@gmail.com
License: MIT
Platform: UNKNOWN
Classifier: License :: OSI Approved :: MIT License
Classifier: Programming Language :: Python :: 3
Classifier: Programming Language :: Python :: 3.6
Classifier: Programming Language :: Python :: 3.7
Classifier: Programming Language :: Python :: 3.8
Requires-Python: >=3.6
Requires-Dist: click (==7.1.*)
Requires-Dist: orjson (==3.4.*)
Requires-Dist: PyYAML (==5.3.*)
Requires-Dist: pandas (==1.1.*)
Requires-Dist: psycopg2 (==2.8.*)
Requires-Dist: SQLAlchemy (==1.3.*)
